[
  {
    "strategy": "ls_fade",
    "train_trades": 37597,
    "test_trades": 10707,
    "baseline_train_calmar": 6.085,
    "baseline_test_calmar": 3.823,
    "vol_filter_low": 4.5,
    "vol_filter_low_calmar": 9.389,
    "vol_filter_high": 22.0,
    "vol_filter_high_calmar": 6.056,
    "validation_status": "VALIDATED",
    "improvement_pct": 54.3
  },
  {
    "strategy": "mean_reversion",
    "train_trades": 5116,
    "test_trades": 1586,
    "baseline_train_calmar": 5.395,
    "baseline_test_calmar": 3.587,
    "vol_filter_low": 0.0,
    "vol_filter_low_calmar": 5.395,
    "vol_filter_high": 25.0,
    "vol_filter_high_calmar": 5.36,
    "validation_status": "VALIDATED",
    "improvement_pct": 0.0
  },
  {
    "strategy": "momentum",
    "train_trades": 33068,
    "test_trades": 13880,
    "baseline_train_calmar": 5.088,
    "baseline_test_calmar": 0.94,
    "vol_filter_low": 2.0,
    "vol_filter_low_calmar": 5.185,
    "vol_filter_high": 25.0,
    "vol_filter_high_calmar": 5.059,
    "validation_status": "VALIDATED",
    "improvement_pct": 1.9
  },
  {
    "strategy": "momentum_ls",
    "train_trades": 19783,
    "test_trades": 9957,
    "baseline_train_calmar": 5.482,
    "baseline_test_calmar": 2.77,
    "vol_filter_low": 4.5,
    "vol_filter_low_calmar": 5.566,
    "vol_filter_high": 25.0,
    "vol_filter_high_calmar": 5.469,
    "validation_status": "VALIDATED",
    "improvement_pct": 1.5
  },
  {
    "strategy": "reversal",
    "train_trades": 7075,
    "test_trades": 2938,
    "baseline_train_calmar": 1.101,
    "baseline_test_calmar": 0.656,
    "vol_filter_low": 7.5,
    "vol_filter_low_calmar": 1.732,
    "vol_filter_high": 21.0,
    "vol_filter_high_calmar": 1.25,
    "validation_status": "VALIDATED",
    "improvement_pct": 57.3
  }
]